Metadata-Version: 1.1
Name: coinmarketcappy
Version: 0.1.0
Summary: Python API wrapper and scraper for coinmarketcap data
Home-page: https://github.com/saporitigianni/coinmarketcappy
Author: Gianni Saporiti
Author-email: saporitigianni@outlook.com
License: MIT
Download-URL: https://pypi.python.org/pypi/coinmarketcappy
Keywords: forex,api,currencies,financial
Platform: UNKNOWN
Classifier: Development Status :: 3 - Alpha
Classifier: Intended Audience :: Developers
Classifier: Intended Audience :: Financial and Insurance Industry
Classifier: License :: OSI Approved :: MIT License
Classifier: Operating System :: OS Independent
Classifier: Programming Language :: Python :: 3
Classifier: Topic :: Office/Business :: Financial
Classifier: Topic :: Software Development :: Build Tools
